pysysid/__init__.py
pysysid/classical.py
pysysid/util.py
pysysid-0.1.0.dist-info/LICENSE
pysysid-0.1.0.dist-info/METADATA
pysysid-0.1.0.dist-info/WHEEL
pysysid-0.1.0.dist-info/top_level.txt
pysysid-0.1.0.dist-info/RECORD
